flask_easyjwt/__init__.py
flask_easyjwt/flask_easyjwt.py
flask_easyjwt-0.2.2.dist-info/LICENSE
flask_easyjwt-0.2.2.dist-info/METADATA
flask_easyjwt-0.2.2.dist-info/WHEEL
flask_easyjwt-0.2.2.dist-info/top_level.txt
flask_easyjwt-0.2.2.dist-info/RECORD
