Metadata-Version: 2.1
Name: flask-easyjwt
Version: 0.2.2
Summary: Super simple JSON Web Tokens for Flask
Home-page: https://github.com/BMeu/Flask-EasyJWT
Author: Bastian Meyer
Author-email: bastian@bastianmeyer.eu
License: UNKNOWN
Project-URL: Documentation, https://flask-easyjwt.readthedocs.io/en/latest/
Project-URL: Source, https://github.com/BMeu/Flask-EasyJWT
Project-URL: Tracker, https://github.com/BMeu/Flask-EasyJWT/issues
Keywords: jwt token tokens JSON Flask
Platform: any
Classifier: Development Status :: 4 - Beta
Classifier: Environment :: Web Environment
Classifier: Framework :: Flask
Classifier: Intended Audience :: Developers
Classifier: License :: OSI Approved :: MIT License
Classifier: Operating System :: OS Independent
Classifier: Programming Language :: Python :: 3
Classifier: Programming Language :: Python :: 3.6
Classifier: Programming Language :: Python :: 3.7
Classifier: Programming Language :: Python :: 3.8
Classifier: Programming Language :: Python :: 3.9
Classifier: Topic :: Internet
Classifier: Topic :: Internet :: WWW/HTTP :: Dynamic Content
Classifier: Topic :: Software Development :: Libraries :: Python Modules
Requires-Python: >=3.6
Requires-Dist: easyjwt (==0.2.*)
Requires-Dist: Flask (>=1.0)
